nonebot_plugin_pokesomeone/__init__.py
nonebot_plugin_pokesomeone/config.py
nonebot_plugin_pokesomeone-0.1.1.dist-info/METADATA
nonebot_plugin_pokesomeone-0.1.1.dist-info/WHEEL
nonebot_plugin_pokesomeone-0.1.1.dist-info/RECORD
