Metadata-Version: 2.1
Name: nonebot-plugin-pokesomeone
Version: 0.1.1
Summary: 指定戳一戳
Author: canxin
Author-email: 1969730106@qq.com
Requires-Python: >=3.8,<4.0
Classifier: Programming Language :: Python :: 3
Classifier: Programming Language :: Python :: 3.8
Classifier: Programming Language :: Python :: 3.9
Classifier: Programming Language :: Python :: 3.10
Classifier: Programming Language :: Python :: 3.11
Requires-Dist: nonebot-adapter-onebot (>=2.2.3,<3.0.0)
Requires-Dist: nonebot2 (>=2.0.0,<3.0.0)
